manju_humantime/__init__.py
manju_humantime/humanize.py
manju_humantime-0.1.2.dist-info/licenses/LICENSE
manju_humantime-0.1.2.dist-info/METADATA
manju_humantime-0.1.2.dist-info/WHEEL
manju_humantime-0.1.2.dist-info/top_level.txt
manju_humantime-0.1.2.dist-info/RECORD
