Metadata-Version: 2.4
Name: manju-humantime
Version: 0.1.2
Summary: A simple utility to humanize time differences.
Home-page: https://github.com/manjumh021/manju-humantime
Author: Manjunathgouda MH
Author-email: Manjunathgouda MH <manjumh021@gmail.com>
License: MIT
Project-URL: Homepage, https://github.com/manjumh021/manju-humantime
Project-URL: Repository, https://github.com/manjumh021/manju-humantime
Requires-Python: >=3.6
License-File: LICENSE
Dynamic: author
Dynamic: home-page
Dynamic: license-file
Dynamic: requires-python
